helen/__init__.py
helen/helen.py
helen/helen_train.py
helen/marginpolish.py
helen/version.py
helen/bin/marginPolish
helen/build/HELEN.cpython-36m-darwin.so
helen/modules/python/CallConsensusInterface.py
helen/modules/python/DataStore.py
helen/modules/python/DownloadModel.py
helen/modules/python/FileManager.py
helen/modules/python/Options.py
helen/modules/python/PairwiseAlignment.py
helen/modules/python/PolishInterface.py
helen/modules/python/Stitch.py
helen/modules/python/StitchInterface.py
helen/modules/python/TestInterface.py
helen/modules/python/TextColor.py
helen/modules/python/TrainInterface.py
helen/modules/python/__init__.py
helen/modules/python/hyperbandInterface.py
helen/modules/python/helper/VCF_remove_phase.py
helen/modules/python/helper/__init__.py
helen/modules/python/helper/assess_summary_analyzer.py
helen/modules/python/helper/csv_analyzer.py
helen/modules/python/helper/hdf5_reader.py
helen/modules/python/helper/quast_sv_extractor.py
helen/modules/python/helper/tensor_analyzer.py
helen/modules/python/helper/test_pairwisealigner.py
helen/modules/python/models/ModelHander.py
helen/modules/python/models/TransducerModel.py
helen/modules/python/models/__init__.py
helen/modules/python/models/dataloader.py
helen/modules/python/models/dataloader_debug.py
helen/modules/python/models/dataloader_predict.py
helen/modules/python/models/hyperband.py
helen/modules/python/models/predict.py
helen/modules/python/models/predict_cpu.py
helen/modules/python/models/predict_gpu.py
helen/modules/python/models/test.py
helen/modules/python/models/test_debug.py
helen/modules/python/models/train.py
helen/modules/python/models/train_distributed.py
helen-0.0.23.dist-info/LICENSE
helen-0.0.23.dist-info/METADATA
helen-0.0.23.dist-info/WHEEL
helen-0.0.23.dist-info/entry_points.txt
helen-0.0.23.dist-info/top_level.txt
helen-0.0.23.dist-info/RECORD
