Metadata-Version: 2.1
Name: helen
Version: 0.0.23
Summary: RNN based assembly HELEN. It works paired with MarginPolish.
Home-page: https://github.com/kishwarshafin/helen
Author: Kishwar Shafin
Author-email: kishwar.shafin@gmail.com
License: UNKNOWN
Platform: UNKNOWN
Requires-Python: >=3.5.*
Requires-Dist: h5py
Requires-Dist: tqdm
Requires-Dist: numpy
Requires-Dist: wget
Requires-Dist: torch
Requires-Dist: torchvision
Requires-Dist: torchnet
Requires-Dist: pyyaml
Requires-Dist: onnx
Requires-Dist: onnxruntime
Requires-Dist: hyperopt
Requires-Dist: matplotlib
